girc/__init__.py
girc/asyncio_compat.py
girc/capabilities.py
girc/client.py
girc/events.py
girc/features.py
girc/formatting.py
girc/imapping.py
girc/info.py
girc/types.py
girc/utils.py
girc/ircreactor/__init__.py
girc/ircreactor/envelope.py
girc/ircreactor/events.py
girc/ircreactor/reactor.py
girc-0.4.0.data/scripts/girc_test
tests/__init__.py
tests/test_formatting.py
tests/test_parse.py
tests/test_utils.py
girc-0.4.0.dist-info/LICENSE
girc-0.4.0.dist-info/LICENSE.ircreactor
girc-0.4.0.dist-info/METADATA
girc-0.4.0.dist-info/WHEEL
girc-0.4.0.dist-info/top_level.txt
girc-0.4.0.dist-info/RECORD
