Metadata-Version: 2.1
Name: girc
Version: 0.4.0
Summary: A modern Python IRC library for Python 3.4, based on asyncio. In Development.
Home-page: https://github.com/DanielOaks/girc
Author: Daniel Oaks
Author-email: daniel@danieloaks.net
License: UNKNOWN
Platform: UNKNOWN
Classifier: Development Status :: 3 - Alpha
Classifier: Intended Audience :: Developers
Classifier: Natural Language :: English
Classifier: License :: OSI Approved :: ISC License (ISCL)
Classifier: Programming Language :: Python :: 3.4
Classifier: Programming Language :: Python :: 3.5
Classifier: Programming Language :: Python :: 3.6
Classifier: Programming Language :: Python :: 3.7
Classifier: Programming Language :: Python :: 3 :: Only
Classifier: Topic :: Communications :: Chat
Classifier: Topic :: Communications :: Chat :: Internet Relay Chat
Requires-Dist: docopt
